async_framework/__init__.py
async_framework/apps.py
async_framework/middleware.py
async_framework/orm.py
async_framework/tasks.py
async_framework/throttle.py
async_framework/utils.py
async_framework/views/__init__.py
async_framework/views/api.py
async_framework/views/core.py
async_framework/views/service_resolver.py
djangoasyncframework-0.3.8.dist-info/licenses/LICENSE
tests/__init__.py
tests/conftest.py
tests/django_config.py
tests/middleware/__init__.py
tests/middleware/test_async_error_middleware.py
tests/utils/__init__.py
tests/utils/test_async_task.py
tests/utils/test_run_in_background.py
tests/views/__init__.py
tests/views/api/__init__.py
tests/views/api/test_async_api_view.py
tests/views/core/__init__.py
tests/views/core/test_async_view.py
djangoasyncframework-0.3.8.dist-info/METADATA
djangoasyncframework-0.3.8.dist-info/WHEEL
djangoasyncframework-0.3.8.dist-info/top_level.txt
djangoasyncframework-0.3.8.dist-info/RECORD
