Metadata-Version: 2.4
Name: djangoasyncframework
Version: 0.3.8
Summary:  Providing async views, ORM, and tasks for Django. 
Home-page: https://github.com/mmasri1/django-async-framework
Author: mmasri
Author-email: mouhamaddev04@gmail.com
Classifier: Programming Language :: Python :: 3
Classifier: Framework :: Django
Classifier: License :: OSI Approved :: BSD License
Classifier: Operating System :: OS Independent
Requires-Python: >=3.6
License-File: LICENSE
Dynamic: author
Dynamic: author-email
Dynamic: classifier
Dynamic: description
Dynamic: description-content-type
Dynamic: home-page
Dynamic: license-file
Dynamic: requires-python
Dynamic: summary
